{
  "pulled_at": "2026-02-21T20:01:19.215202",
  "as_of_date": "2026-02-21",
  "delta_base_date": "2026-02-14",
  "alliance_count": 175,
  "alliances": [
    {
      "alliance_id": 2063151130,
      "alliance_tag": "THC",
      "rank": 1,
      "member_count": 71,
      "total_power": 648768503,
      "avg_level": 28,
      "max_level": 50,
      "total_pvp": 4805,
      "total_hk": 817510,
      "total_mined": 1072642518,
      "total_raided": 255647813339,
      "power_delta_7d": 648768503
    },
    {
      "alliance_id": 4118638119,
      "alliance_tag": "OAK",
      "rank": 2,
      "member_count": 24,
      "total_power": 481048098,
      "avg_level": 28,
      "max_level": 50,
      "total_pvp": 13221,
      "total_hk": 415836,
      "total_mined": 990265539,
      "total_raided": 1335930420685,
      "power_delta_7d": 481048098
    },
    {
      "alliance_id": 3974286889,
      "alliance_tag": "NCC",
      "rank": 3,
      "member_count": 32,
      "total_power": 323497576,
      "avg_level": 26,
      "max_level": 49,
      "total_pvp": 1283,
      "total_hk": 297670,
      "total_mined": 289429513,
      "total_raided": 68751820861,
      "power_delta_7d": 23326828
    },
    {
      "alliance_id": 2688328612,
      "alliance_tag": "TGS",
      "rank": 4,
      "member_count": 61,
      "total_power": 281370006,
      "avg_level": 25,
      "max_level": 45,
      "total_pvp": 3490,
      "total_hk": 275549,
      "total_mined": 206418977,
      "total_raided": 945880437,
      "power_delta_7d": 281370006
    },
    {
      "alliance_id": 3849094569,
      "alliance_tag": "STFC",
      "rank": 5,
      "member_count": 46,
      "total_power": 116750964,
      "avg_level": 22,
      "max_level": 46,
      "total_pvp": 658,
      "total_hk": 191884,
      "total_mined": 107335307,
      "total_raided": 16990122,
      "power_delta_7d": 116750964
    },
    {
      "alliance_id": 276153909,
      "alliance_tag": "SHBU",
      "rank": 6,
      "member_count": 20,
      "total_power": 82894470,
      "avg_level": 18,
      "max_level": 50,
      "total_pvp": 63,
      "total_hk": 13138,
      "total_mined": 26153928,
      "total_raided": 17673,
      "power_delta_7d": 82894470
    },
    {
      "alliance_id": 1643099756,
      "alliance_tag": "FBN",
      "rank": 7,
      "member_count": 51,
      "total_power": 76135959,
      "avg_level": 19,
      "max_level": 42,
      "total_pvp": 1590,
      "total_hk": 131374,
      "total_mined": 68572569,
      "total_raided": 1145567,
      "power_delta_7d": 76135959
    },
    {
      "alliance_id": 2195127416,
      "alliance_tag": "SBI",
      "rank": 8,
      "member_count": 3,
      "total_power": 60512679,
      "avg_level": 34,
      "max_level": 48,
      "total_pvp": 40,
      "total_hk": 34702,
      "total_mined": 99560744,
      "total_raided": 38434,
      "power_delta_7d": 60512679
    },
    {
      "alliance_id": 2857064901,
      "alliance_tag": "DED",
      "rank": 9,
      "member_count": 3,
      "total_power": 51862335,
      "avg_level": 27,
      "max_level": 47,
      "total_pvp": 32,
      "total_hk": 169044,
      "total_mined": 43611029,
      "total_raided": 26374326,
      "power_delta_7d": 51862335
    },
    {
      "alliance_id": 93214369,
      "alliance_tag": "NEWB",
      "rank": 10,
      "member_count": 51,
      "total_power": 48194864,
      "avg_level": 17,
      "max_level": 43,
      "total_pvp": 137,
      "total_hk": 33846,
      "total_mined": 26038834,
      "total_raided": 34535,
      "power_delta_7d": 48194864
    },
    {
      "alliance_id": 1562620843,
      "alliance_tag": "OTF",
      "rank": 11,
      "member_count": 17,
      "total_power": 47639648,
      "avg_level": 23,
      "max_level": 39,
      "total_pvp": 125,
      "total_hk": 106204,
      "total_mined": 35777127,
      "total_raided": 18901,
      "power_delta_7d": 47639648
    },
    {
      "alliance_id": 2219091017,
      "alliance_tag": "BLU",
      "rank": 12,
      "member_count": 28,
      "total_power": 44511922,
      "avg_level": 18,
      "max_level": 42,
      "total_pvp": 373,
      "total_hk": 23209,
      "total_mined": 5958808,
      "total_raided": 37590,
      "power_delta_7d": 44511922
    },
    {
      "alliance_id": 4004077626,
      "alliance_tag": "NF",
      "rank": 13,
      "member_count": 1,
      "total_power": 32372544,
      "avg_level": 46,
      "max_level": 46,
      "total_pvp": 6,
      "total_hk": 2913,
      "total_mined": 761421,
      "total_raided": 487546,
      "power_delta_7d": 32372544
    },
    {
      "alliance_id": 1846965200,
      "alliance_tag": "CBD",
      "rank": 14,
      "member_count": 1,
      "total_power": 32004605,
      "avg_level": 45,
      "max_level": 45,
      "total_pvp": 8,
      "total_hk": 6056,
      "total_mined": 6703473,
      "total_raided": 0,
      "power_delta_7d": 32004605
    },
    {
      "alliance_id": 598156299,
      "alliance_tag": "DWT",
      "rank": 15,
      "member_count": 46,
      "total_power": 31134563,
      "avg_level": 18,
      "max_level": 35,
      "total_pvp": 589,
      "total_hk": 80401,
      "total_mined": 33600826,
      "total_raided": 88873,
      "power_delta_7d": 31134563
    },
    {
      "alliance_id": 3492754188,
      "alliance_tag": "RUN",
      "rank": 16,
      "member_count": 44,
      "total_power": 30407209,
      "avg_level": 17,
      "max_level": 36,
      "total_pvp": 289,
      "total_hk": 52192,
      "total_mined": 40912782,
      "total_raided": 29300,
      "power_delta_7d": 30407209
    },
    {
      "alliance_id": 3343513278,
      "alliance_tag": "MACO",
      "rank": 17,
      "member_count": 38,
      "total_power": 27183060,
      "avg_level": 18,
      "max_level": 35,
      "total_pvp": 200,
      "total_hk": 30673,
      "total_mined": 16860614,
      "total_raided": 23236,
      "power_delta_7d": 27183060
    },
    {
      "alliance_id": 3739984292,
      "alliance_tag": "BUZZ",
      "rank": 18,
      "member_count": 45,
      "total_power": 27137396,
      "avg_level": 17,
      "max_level": 33,
      "total_pvp": 292,
      "total_hk": 46884,
      "total_mined": 19579321,
      "total_raided": 77477,
      "power_delta_7d": 27137396
    },
    {
      "alliance_id": 525120447,
      "alliance_tag": "WIFI",
      "rank": 19,
      "member_count": 55,
      "total_power": 21669276,
      "avg_level": 17,
      "max_level": 30,
      "total_pvp": 1275,
      "total_hk": 83150,
      "total_mined": 27080092,
      "total_raided": 163681,
      "power_delta_7d": 21669276
    },
    {
      "alliance_id": 513347412,
      "alliance_tag": "GSF",
      "rank": 20,
      "member_count": 30,
      "total_power": 20630290,
      "avg_level": 16,
      "max_level": 40,
      "total_pvp": 144,
      "total_hk": 15338,
      "total_mined": 2542694,
      "total_raided": 20169,
      "power_delta_7d": 20630290
    },
    {
      "alliance_id": 1286139301,
      "alliance_tag": "RLX",
      "rank": 21,
      "member_count": 18,
      "total_power": 19500863,
      "avg_level": 17,
      "max_level": 39,
      "total_pvp": 264,
      "total_hk": 13596,
      "total_mined": 4316441,
      "total_raided": 78433,
      "power_delta_7d": 19500863
    },
    {
      "alliance_id": 2268158412,
      "alliance_tag": "SPCY",
      "rank": 22,
      "member_count": 51,
      "total_power": 18286937,
      "avg_level": 17,
      "max_level": 31,
      "total_pvp": 375,
      "total_hk": 46134,
      "total_mined": 12970982,
      "total_raided": 56352,
      "power_delta_7d": 18286937
    },
    {
      "alliance_id": 3919572785,
      "alliance_tag": "GRN",
      "rank": 23,
      "member_count": 1,
      "total_power": 18122976,
      "avg_level": 42,
      "max_level": 42,
      "total_pvp": 13,
      "total_hk": 499,
      "total_mined": 471895,
      "total_raided": 0,
      "power_delta_7d": 18122976
    },
    {
      "alliance_id": 39602231,
      "alliance_tag": "SD",
      "rank": 24,
      "member_count": 20,
      "total_power": 17115823,
      "avg_level": 18,
      "max_level": 32,
      "total_pvp": 96,
      "total_hk": 21361,
      "total_mined": 4426317,
      "total_raided": 21257,
      "power_delta_7d": 17115823
    },
    {
      "alliance_id": 634810268,
      "alliance_tag": "JTF",
      "rank": 25,
      "member_count": 32,
      "total_power": 13907988,
      "avg_level": 16,
      "max_level": 38,
      "total_pvp": 273,
      "total_hk": 22249,
      "total_mined": 7764712,
      "total_raided": 56451,
      "power_delta_7d": 13907988
    },
    {
      "alliance_id": 166250396,
      "alliance_tag": "NYT",
      "rank": 26,
      "member_count": 32,
      "total_power": 13528209,
      "avg_level": 17,
      "max_level": 33,
      "total_pvp": 85,
      "total_hk": 33209,
      "total_mined": 5819674,
      "total_raided": 14460,
      "power_delta_7d": 13528209
    },
    {
      "alliance_id": 3090623212,
      "alliance_tag": "AZN",
      "rank": 27,
      "member_count": 39,
      "total_power": 13457134,
      "avg_level": 17,
      "max_level": 31,
      "total_pvp": 197,
      "total_hk": 28640,
      "total_mined": 10554992,
      "total_raided": 60599,
      "power_delta_7d": 13457134
    },
    {
      "alliance_id": 3706369634,
      "alliance_tag": "MC",
      "rank": 28,
      "member_count": 32,
      "total_power": 12028467,
      "avg_level": 16,
      "max_level": 35,
      "total_pvp": 133,
      "total_hk": 15682,
      "total_mined": 3842857,
      "total_raided": 16875,
      "power_delta_7d": 12028467
    },
    {
      "alliance_id": 3347999877,
      "alliance_tag": "HELL",
      "rank": 29,
      "member_count": 1,
      "total_power": 11634250,
      "avg_level": 38,
      "max_level": 38,
      "total_pvp": 84,
      "total_hk": 7480,
      "total_mined": 9881591,
      "total_raided": 11850,
      "power_delta_7d": 11634250
    },
    {
      "alliance_id": 3370539474,
      "alliance_tag": "ΩΘΩ",
      "rank": 30,
      "member_count": 1,
      "total_power": 10694185,
      "avg_level": 41,
      "max_level": 41,
      "total_pvp": 27,
      "total_hk": 1242,
      "total_mined": 319149,
      "total_raided": 0,
      "power_delta_7d": 10694185
    },
    {
      "alliance_id": 3817945019,
      "alliance_tag": "ORN",
      "rank": 31,
      "member_count": 29,
      "total_power": 9318874,
      "avg_level": 15,
      "max_level": 35,
      "total_pvp": 154,
      "total_hk": 10762,
      "total_mined": 1967175,
      "total_raided": 33122,
      "power_delta_7d": 9318874
    },
    {
      "alliance_id": 1459803168,
      "alliance_tag": "SRF",
      "rank": 32,
      "member_count": 37,
      "total_power": 9076327,
      "avg_level": 15,
      "max_level": 28,
      "total_pvp": 152,
      "total_hk": 16976,
      "total_mined": 5050586,
      "total_raided": 33925,
      "power_delta_7d": 9076327
    },
    {
      "alliance_id": 1311843732,
      "alliance_tag": "WOK",
      "rank": 33,
      "member_count": 41,
      "total_power": 8529157,
      "avg_level": 16,
      "max_level": 26,
      "total_pvp": 247,
      "total_hk": 22314,
      "total_mined": 6509470,
      "total_raided": 27424,
      "power_delta_7d": 8529157
    },
    {
      "alliance_id": 416102132,
      "alliance_tag": "DEVI",
      "rank": 34,
      "member_count": 38,
      "total_power": 7909256,
      "avg_level": 15,
      "max_level": 27,
      "total_pvp": 71,
      "total_hk": 19067,
      "total_mined": 4656891,
      "total_raided": 18585,
      "power_delta_7d": 7909256
    },
    {
      "alliance_id": 3260034908,
      "alliance_tag": "WARG",
      "rank": 35,
      "member_count": 36,
      "total_power": 7776800,
      "avg_level": 16,
      "max_level": 26,
      "total_pvp": 326,
      "total_hk": 18955,
      "total_mined": 11582716,
      "total_raided": 38608,
      "power_delta_7d": 7776800
    },
    {
      "alliance_id": 3722758068,
      "alliance_tag": "AGN",
      "rank": 36,
      "member_count": 31,
      "total_power": 5695293,
      "avg_level": 16,
      "max_level": 25,
      "total_pvp": 58,
      "total_hk": 15281,
      "total_mined": 2514398,
      "total_raided": 9980,
      "power_delta_7d": 5695293
    },
    {
      "alliance_id": 1488426316,
      "alliance_tag": "SIN",
      "rank": 37,
      "member_count": 16,
      "total_power": 5417981,
      "avg_level": 16,
      "max_level": 26,
      "total_pvp": 166,
      "total_hk": 7687,
      "total_mined": 2541949,
      "total_raided": 40759,
      "power_delta_7d": 5417981
    },
    {
      "alliance_id": 2725281106,
      "alliance_tag": "MD",
      "rank": 38,
      "member_count": 26,
      "total_power": 4804184,
      "avg_level": 16,
      "max_level": 28,
      "total_pvp": 47,
      "total_hk": 17582,
      "total_mined": 2444954,
      "total_raided": 5396,
      "power_delta_7d": 4804184
    },
    {
      "alliance_id": 2285003101,
      "alliance_tag": "SOPI",
      "rank": 39,
      "member_count": 16,
      "total_power": 4243727,
      "avg_level": 16,
      "max_level": 23,
      "total_pvp": 91,
      "total_hk": 13809,
      "total_mined": 3703803,
      "total_raided": 18858,
      "power_delta_7d": 4243727
    },
    {
      "alliance_id": 2823242860,
      "alliance_tag": "CUNK",
      "rank": 40,
      "member_count": 8,
      "total_power": 3957280,
      "avg_level": 19,
      "max_level": 28,
      "total_pvp": 117,
      "total_hk": 5212,
      "total_mined": 1297877,
      "total_raided": 38157,
      "power_delta_7d": 3957280
    },
    {
      "alliance_id": 3409020803,
      "alliance_tag": "GGI",
      "rank": 41,
      "member_count": 3,
      "total_power": 3907700,
      "avg_level": 22,
      "max_level": 27,
      "total_pvp": 20,
      "total_hk": 7533,
      "total_mined": 2161399,
      "total_raided": 4165,
      "power_delta_7d": 3907700
    },
    {
      "alliance_id": 4195137728,
      "alliance_tag": "NTG",
      "rank": 42,
      "member_count": 18,
      "total_power": 3906107,
      "avg_level": 15,
      "max_level": 26,
      "total_pvp": 174,
      "total_hk": 12519,
      "total_mined": 2205870,
      "total_raided": 32828,
      "power_delta_7d": 3906107
    },
    {
      "alliance_id": 303126559,
      "alliance_tag": "GIRB",
      "rank": 43,
      "member_count": 19,
      "total_power": 3835019,
      "avg_level": 16,
      "max_level": 19,
      "total_pvp": 289,
      "total_hk": 18186,
      "total_mined": 7050828,
      "total_raided": 68858,
      "power_delta_7d": 3835019
    },
    {
      "alliance_id": 3186902654,
      "alliance_tag": "SOV",
      "rank": 44,
      "member_count": 20,
      "total_power": 3819437,
      "avg_level": 16,
      "max_level": 25,
      "total_pvp": 142,
      "total_hk": 7283,
      "total_mined": 1343308,
      "total_raided": 19102,
      "power_delta_7d": 3819437
    },
    {
      "alliance_id": 1105243672,
      "alliance_tag": "GNA",
      "rank": 45,
      "member_count": 7,
      "total_power": 3645004,
      "avg_level": 17,
      "max_level": 25,
      "total_pvp": 16,
      "total_hk": 3859,
      "total_mined": 1602719,
      "total_raided": 3101,
      "power_delta_7d": 3645004
    },
    {
      "alliance_id": 902799471,
      "alliance_tag": "ÌĽÀ",
      "rank": 46,
      "member_count": 30,
      "total_power": 3547332,
      "avg_level": 15,
      "max_level": 19,
      "total_pvp": 68,
      "total_hk": 10512,
      "total_mined": 3651309,
      "total_raided": 15647,
      "power_delta_7d": 3547332
    },
    {
      "alliance_id": 1556043901,
      "alliance_tag": "BORG",
      "rank": 47,
      "member_count": 3,
      "total_power": 3470092,
      "avg_level": 20,
      "max_level": 28,
      "total_pvp": 27,
      "total_hk": 17626,
      "total_mined": 3878805,
      "total_raided": 3137,
      "power_delta_7d": 3470092
    },
    {
      "alliance_id": 1520176283,
      "alliance_tag": "TS",
      "rank": 48,
      "member_count": 17,
      "total_power": 3386862,
      "avg_level": 16,
      "max_level": 23,
      "total_pvp": 64,
      "total_hk": 7207,
      "total_mined": 1097428,
      "total_raided": 21326,
      "power_delta_7d": 3386862
    },
    {
      "alliance_id": 1808854888,
      "alliance_tag": "WOTT",
      "rank": 49,
      "member_count": 23,
      "total_power": 3281717,
      "avg_level": 15,
      "max_level": 19,
      "total_pvp": 165,
      "total_hk": 13426,
      "total_mined": 4982743,
      "total_raided": 23899,
      "power_delta_7d": 3281717
    },
    {
      "alliance_id": 375560774,
      "alliance_tag": "NFE",
      "rank": 50,
      "member_count": 29,
      "total_power": 3268374,
      "avg_level": 15,
      "max_level": 19,
      "total_pvp": 98,
      "total_hk": 12774,
      "total_mined": 2310191,
      "total_raided": 29465,
      "power_delta_7d": 3268374
    },
    {
      "alliance_id": 3750013621,
      "alliance_tag": "RES",
      "rank": 51,
      "member_count": 29,
      "total_power": 3126346,
      "avg_level": 15,
      "max_level": 19,
      "total_pvp": 42,
      "total_hk": 5609,
      "total_mined": 963501,
      "total_raided": 5780,
      "power_delta_7d": 3126346
    },
    {
      "alliance_id": 2624092139,
      "alliance_tag": "STS",
      "rank": 52,
      "member_count": 31,
      "total_power": 3108438,
      "avg_level": 14,
      "max_level": 19,
      "total_pvp": 42,
      "total_hk": 11478,
      "total_mined": 3915716,
      "total_raided": 10069,
      "power_delta_7d": 3108438
    },
    {
      "alliance_id": 3678342509,
      "alliance_tag": "PTA",
      "rank": 53,
      "member_count": 26,
      "total_power": 3051594,
      "avg_level": 15,
      "max_level": 20,
      "total_pvp": 29,
      "total_hk": 10456,
      "total_mined": 2732412,
      "total_raided": 4587,
      "power_delta_7d": 3051594
    },
    {
      "alliance_id": 1782949979,
      "alliance_tag": "LUA",
      "rank": 54,
      "member_count": 2,
      "total_power": 2926852,
      "avg_level": 22,
      "max_level": 26,
      "total_pvp": 13,
      "total_hk": 7581,
      "total_mined": 3946330,
      "total_raided": 1408,
      "power_delta_7d": 2926852
    },
    {
      "alliance_id": 1649590652,
      "alliance_tag": "GW",
      "rank": 55,
      "member_count": 9,
      "total_power": 2810211,
      "avg_level": 17,
      "max_level": 25,
      "total_pvp": 15,
      "total_hk": 4045,
      "total_mined": 759420,
      "total_raided": 4233,
      "power_delta_7d": 2810211
    },
    {
      "alliance_id": 4206848789,
      "alliance_tag": "SLG",
      "rank": 56,
      "member_count": 1,
      "total_power": 2797710,
      "avg_level": 25,
      "max_level": 25,
      "total_pvp": 2,
      "total_hk": 4025,
      "total_mined": 1216198,
      "total_raided": 0,
      "power_delta_7d": 2797710
    },
    {
      "alliance_id": 2225102293,
      "alliance_tag": "DNR",
      "rank": 57,
      "member_count": 22,
      "total_power": 2761164,
      "avg_level": 16,
      "max_level": 20,
      "total_pvp": 166,
      "total_hk": 9012,
      "total_mined": 2240634,
      "total_raided": 39369,
      "power_delta_7d": 2761164
    },
    {
      "alliance_id": 551062524,
      "alliance_tag": "GRA",
      "rank": 58,
      "member_count": 33,
      "total_power": 2434870,
      "avg_level": 14,
      "max_level": 19,
      "total_pvp": 27,
      "total_hk": 9878,
      "total_mined": 1369980,
      "total_raided": 12341,
      "power_delta_7d": 2434870
    },
    {
      "alliance_id": 450376446,
      "alliance_tag": "STON",
      "rank": 59,
      "member_count": 22,
      "total_power": 2394570,
      "avg_level": 15,
      "max_level": 20,
      "total_pvp": 115,
      "total_hk": 9937,
      "total_mined": 3507251,
      "total_raided": 22999,
      "power_delta_7d": 2394570
    },
    {
      "alliance_id": 4179828469,
      "alliance_tag": "FDF",
      "rank": 60,
      "member_count": 4,
      "total_power": 2363835,
      "avg_level": 17,
      "max_level": 23,
      "total_pvp": 68,
      "total_hk": 2897,
      "total_mined": 639049,
      "total_raided": 10508,
      "power_delta_7d": 2363835
    },
    {
      "alliance_id": 4135287836,
      "alliance_tag": "MMM",
      "rank": 61,
      "member_count": 1,
      "total_power": 2263645,
      "avg_level": 25,
      "max_level": 25,
      "total_pvp": 1,
      "total_hk": 4305,
      "total_mined": 779331,
      "total_raided": 0,
      "power_delta_7d": 2263645
    },
    {
      "alliance_id": 2243232420,
      "alliance_tag": "ARG",
      "rank": 62,
      "member_count": 17,
      "total_power": 2185145,
      "avg_level": 15,
      "max_level": 19,
      "total_pvp": 185,
      "total_hk": 10067,
      "total_mined": 1527811,
      "total_raided": 24373,
      "power_delta_7d": 2185145
    },
    {
      "alliance_id": 2890123027,
      "alliance_tag": "WZA",
      "rank": 63,
      "member_count": 1,
      "total_power": 2175152,
      "avg_level": 26,
      "max_level": 26,
      "total_pvp": 4,
      "total_hk": 1450,
      "total_mined": 724069,
      "total_raided": 0,
      "power_delta_7d": 2175152
    },
    {
      "alliance_id": 3588596345,
      "alliance_tag": "DR",
      "rank": 64,
      "member_count": 13,
      "total_power": 2117253,
      "avg_level": 15,
      "max_level": 21,
      "total_pvp": 58,
      "total_hk": 11338,
      "total_mined": 2538710,
      "total_raided": 13973,
      "power_delta_7d": 2117253
    },
    {
      "alliance_id": 2360560935,
      "alliance_tag": "DËMØ",
      "rank": 65,
      "member_count": 21,
      "total_power": 2043366,
      "avg_level": 15,
      "max_level": 19,
      "total_pvp": 38,
      "total_hk": 6361,
      "total_mined": 870304,
      "total_raided": 9015,
      "power_delta_7d": 2043366
    },
    {
      "alliance_id": 949716587,
      "alliance_tag": "FED",
      "rank": 66,
      "member_count": 19,
      "total_power": 1753765,
      "avg_level": 14,
      "max_level": 18,
      "total_pvp": 36,
      "total_hk": 7563,
      "total_mined": 815028,
      "total_raided": 10059,
      "power_delta_7d": 1753765
    },
    {
      "alliance_id": 4161078996,
      "alliance_tag": "MICH",
      "rank": 67,
      "member_count": 11,
      "total_power": 1681812,
      "avg_level": 16,
      "max_level": 19,
      "total_pvp": 87,
      "total_hk": 6457,
      "total_mined": 2433312,
      "total_raided": 16637,
      "power_delta_7d": 1681812
    },
    {
      "alliance_id": 4217254695,
      "alliance_tag": "TAG",
      "rank": 68,
      "member_count": 1,
      "total_power": 1491391,
      "avg_level": 23,
      "max_level": 23,
      "total_pvp": 0,
      "total_hk": 376,
      "total_mined": 70429,
      "total_raided": 0,
      "power_delta_7d": 1491391
    },
    {
      "alliance_id": 146877741,
      "alliance_tag": "OMI",
      "rank": 69,
      "member_count": 7,
      "total_power": 1339314,
      "avg_level": 15,
      "max_level": 19,
      "total_pvp": 10,
      "total_hk": 5836,
      "total_mined": 1676711,
      "total_raided": 1033,
      "power_delta_7d": 1339314
    },
    {
      "alliance_id": 997678106,
      "alliance_tag": "HI",
      "rank": 70,
      "member_count": 1,
      "total_power": 1266557,
      "avg_level": 23,
      "max_level": 23,
      "total_pvp": 3,
      "total_hk": 418,
      "total_mined": 173623,
      "total_raided": 0,
      "power_delta_7d": 1266557
    },
    {
      "alliance_id": 1794557510,
      "alliance_tag": "DK",
      "rank": 71,
      "member_count": 7,
      "total_power": 1168799,
      "avg_level": 16,
      "max_level": 19,
      "total_pvp": 37,
      "total_hk": 10459,
      "total_mined": 2063004,
      "total_raided": 7214,
      "power_delta_7d": 1168799
    },
    {
      "alliance_id": 3427284427,
      "alliance_tag": "HARD",
      "rank": 72,
      "member_count": 7,
      "total_power": 1144393,
      "avg_level": 16,
      "max_level": 19,
      "total_pvp": 54,
      "total_hk": 3268,
      "total_mined": 494257,
      "total_raided": 11582,
      "power_delta_7d": 1144393
    },
    {
      "alliance_id": 1413388534,
      "alliance_tag": "TVHN",
      "rank": 73,
      "member_count": 7,
      "total_power": 1128568,
      "avg_level": 16,
      "max_level": 20,
      "total_pvp": 11,
      "total_hk": 3225,
      "total_mined": 1399428,
      "total_raided": 4468,
      "power_delta_7d": 1128568
    },
    {
      "alliance_id": 1374828905,
      "alliance_tag": "TRUE",
      "rank": 74,
      "member_count": 3,
      "total_power": 974389,
      "avg_level": 17,
      "max_level": 22,
      "total_pvp": 17,
      "total_hk": 4568,
      "total_mined": 1870079,
      "total_raided": 558,
      "power_delta_7d": 974389
    },
    {
      "alliance_id": 37240567,
      "alliance_tag": "JUST",
      "rank": 75,
      "member_count": 1,
      "total_power": 940875,
      "avg_level": 22,
      "max_level": 22,
      "total_pvp": 7,
      "total_hk": 9337,
      "total_mined": 5265374,
      "total_raided": 328,
      "power_delta_7d": 940875
    },
    {
      "alliance_id": 2284648843,
      "alliance_tag": "GLO",
      "rank": 76,
      "member_count": 6,
      "total_power": 908861,
      "avg_level": 15,
      "max_level": 18,
      "total_pvp": 9,
      "total_hk": 2934,
      "total_mined": 230072,
      "total_raided": 1167,
      "power_delta_7d": 908861
    },
    {
      "alliance_id": 3760929921,
      "alliance_tag": "BOB",
      "rank": 77,
      "member_count": 3,
      "total_power": 862890,
      "avg_level": 19,
      "max_level": 19,
      "total_pvp": 198,
      "total_hk": 3668,
      "total_mined": 3158787,
      "total_raided": 6243,
      "power_delta_7d": 862890
    },
    {
      "alliance_id": 2162170862,
      "alliance_tag": "STNK",
      "rank": 78,
      "member_count": 8,
      "total_power": 810454,
      "avg_level": 15,
      "max_level": 19,
      "total_pvp": 33,
      "total_hk": 2903,
      "total_mined": 511407,
      "total_raided": 5194,
      "power_delta_7d": 810454
    },
    {
      "alliance_id": 995310682,
      "alliance_tag": "HOLE",
      "rank": 79,
      "member_count": 6,
      "total_power": 783572,
      "avg_level": 15,
      "max_level": 19,
      "total_pvp": 19,
      "total_hk": 2202,
      "total_mined": 435886,
      "total_raided": 7241,
      "power_delta_7d": 783572
    },
    {
      "alliance_id": 1669884625,
      "alliance_tag": "O",
      "rank": 80,
      "member_count": 7,
      "total_power": 782705,
      "avg_level": 15,
      "max_level": 20,
      "total_pvp": 15,
      "total_hk": 3653,
      "total_mined": 622200,
      "total_raided": 3480,
      "power_delta_7d": 782705
    },
    {
      "alliance_id": 1098983237,
      "alliance_tag": "BRAV",
      "rank": 81,
      "member_count": 8,
      "total_power": 778068,
      "avg_level": 14,
      "max_level": 19,
      "total_pvp": 20,
      "total_hk": 3485,
      "total_mined": 470238,
      "total_raided": 3716,
      "power_delta_7d": 778068
    },
    {
      "alliance_id": 3099235477,
      "alliance_tag": "ECLI",
      "rank": 82,
      "member_count": 4,
      "total_power": 727944,
      "avg_level": 18,
      "max_level": 19,
      "total_pvp": 82,
      "total_hk": 3804,
      "total_mined": 814559,
      "total_raided": 27755,
      "power_delta_7d": 727944
    },
    {
      "alliance_id": 285839082,
      "alliance_tag": "TCG",
      "rank": 83,
      "member_count": 7,
      "total_power": 724317,
      "avg_level": 14,
      "max_level": 19,
      "total_pvp": 2,
      "total_hk": 1671,
      "total_mined": 147318,
      "total_raided": 0,
      "power_delta_7d": 724317
    },
    {
      "alliance_id": 2026267300,
      "alliance_tag": "HOK",
      "rank": 84,
      "member_count": 7,
      "total_power": 652787,
      "avg_level": 15,
      "max_level": 19,
      "total_pvp": 9,
      "total_hk": 1282,
      "total_mined": 231640,
      "total_raided": 450,
      "power_delta_7d": 652787
    },
    {
      "alliance_id": 1095149078,
      "alliance_tag": "DIOS",
      "rank": 85,
      "member_count": 8,
      "total_power": 620911,
      "avg_level": 14,
      "max_level": 18,
      "total_pvp": 8,
      "total_hk": 2076,
      "total_mined": 299736,
      "total_raided": 900,
      "power_delta_7d": 620911
    },
    {
      "alliance_id": 3207946344,
      "alliance_tag": "ATAT",
      "rank": 86,
      "member_count": 2,
      "total_power": 614056,
      "avg_level": 18,
      "max_level": 19,
      "total_pvp": 23,
      "total_hk": 6770,
      "total_mined": 2009909,
      "total_raided": 6629,
      "power_delta_7d": 614056
    },
    {
      "alliance_id": 2267302846,
      "alliance_tag": "KING",
      "rank": 87,
      "member_count": 5,
      "total_power": 597567,
      "avg_level": 16,
      "max_level": 18,
      "total_pvp": 14,
      "total_hk": 1977,
      "total_mined": 133334,
      "total_raided": 2945,
      "power_delta_7d": 597567
    },
    {
      "alliance_id": 2693779752,
      "alliance_tag": "FHFW",
      "rank": 88,
      "member_count": 2,
      "total_power": 562845,
      "avg_level": 18,
      "max_level": 19,
      "total_pvp": 5,
      "total_hk": 1995,
      "total_mined": 1592221,
      "total_raided": 463,
      "power_delta_7d": 562845
    },
    {
      "alliance_id": 2162049438,
      "alliance_tag": "RGVA",
      "rank": 89,
      "member_count": 1,
      "total_power": 555539,
      "avg_level": 19,
      "max_level": 19,
      "total_pvp": 3,
      "total_hk": 6518,
      "total_mined": 784449,
      "total_raided": 0,
      "power_delta_7d": 555539
    },
    {
      "alliance_id": 2305140347,
      "alliance_tag": "SIZZ",
      "rank": 90,
      "member_count": 3,
      "total_power": 525094,
      "avg_level": 16,
      "max_level": 18,
      "total_pvp": 3,
      "total_hk": 2136,
      "total_mined": 878474,
      "total_raided": 1,
      "power_delta_7d": 525094
    },
    {
      "alliance_id": 2061145898,
      "alliance_tag": "GOD",
      "rank": 91,
      "member_count": 2,
      "total_power": 497629,
      "avg_level": 18,
      "max_level": 19,
      "total_pvp": 1,
      "total_hk": 670,
      "total_mined": 61520,
      "total_raided": 0,
      "power_delta_7d": 497629
    },
    {
      "alliance_id": 1361322731,
      "alliance_tag": "AF",
      "rank": 92,
      "member_count": 2,
      "total_power": 481192,
      "avg_level": 18,
      "max_level": 22,
      "total_pvp": 3,
      "total_hk": 662,
      "total_mined": 131771,
      "total_raided": 316,
      "power_delta_7d": 481192
    },
    {
      "alliance_id": 3220761473,
      "alliance_tag": "FIAN",
      "rank": 93,
      "member_count": 1,
      "total_power": 448197,
      "avg_level": 19,
      "max_level": 19,
      "total_pvp": 25,
      "total_hk": 1521,
      "total_mined": 1461827,
      "total_raided": 30,
      "power_delta_7d": 448197
    },
    {
      "alliance_id": 208682474,
      "alliance_tag": "LSF",
      "rank": 94,
      "member_count": 1,
      "total_power": 448147,
      "avg_level": 19,
      "max_level": 19,
      "total_pvp": 16,
      "total_hk": 3011,
      "total_mined": 1349307,
      "total_raided": 3817,
      "power_delta_7d": 448147
    },
    {
      "alliance_id": 3403786709,
      "alliance_tag": "FUN",
      "rank": 95,
      "member_count": 6,
      "total_power": 438387,
      "avg_level": 14,
      "max_level": 16,
      "total_pvp": 16,
      "total_hk": 1615,
      "total_mined": 275262,
      "total_raided": 10612,
      "power_delta_7d": 438387
    },
    {
      "alliance_id": 4148771665,
      "alliance_tag": "FCG",
      "rank": 96,
      "member_count": 1,
      "total_power": 370405,
      "avg_level": 18,
      "max_level": 18,
      "total_pvp": 1,
      "total_hk": 1980,
      "total_mined": 244904,
      "total_raided": 900,
      "power_delta_7d": 370405
    },
    {
      "alliance_id": 2799417213,
      "alliance_tag": "LIVE",
      "rank": 97,
      "member_count": 2,
      "total_power": 284434,
      "avg_level": 14,
      "max_level": 17,
      "total_pvp": 2,
      "total_hk": 1246,
      "total_mined": 304888,
      "total_raided": 0,
      "power_delta_7d": 284434
    },
    {
      "alliance_id": 1064392020,
      "alliance_tag": "CEDA",
      "rank": 98,
      "member_count": 1,
      "total_power": 264814,
      "avg_level": 17,
      "max_level": 17,
      "total_pvp": 1,
      "total_hk": 763,
      "total_mined": 235980,
      "total_raided": 0,
      "power_delta_7d": 264814
    },
    {
      "alliance_id": 2572497473,
      "alliance_tag": "HTL",
      "rank": 99,
      "member_count": 3,
      "total_power": 264187,
      "avg_level": 15,
      "max_level": 15,
      "total_pvp": 1,
      "total_hk": 566,
      "total_mined": 34981,
      "total_raided": 0,
      "power_delta_7d": 264187
    },
    {
      "alliance_id": 2617866693,
      "alliance_tag": "LORE",
      "rank": 100,
      "member_count": 2,
      "total_power": 249564,
      "avg_level": 16,
      "max_level": 19,
      "total_pvp": 7,
      "total_hk": 225,
      "total_mined": 4216,
      "total_raided": 1173,
      "power_delta_7d": 249564
    },
    {
      "alliance_id": 3599780554,
      "alliance_tag": "RETI",
      "rank": 101,
      "member_count": 1,
      "total_power": 246194,
      "avg_level": 18,
      "max_level": 18,
      "total_pvp": 0,
      "total_hk": 953,
      "total_mined": 0,
      "total_raided": 0,
      "power_delta_7d": 246194
    },
    {
      "alliance_id": 3593584721,
      "alliance_tag": "HS",
      "rank": 102,
      "member_count": 1,
      "total_power": 225305,
      "avg_level": 17,
      "max_level": 17,
      "total_pvp": 31,
      "total_hk": 275,
      "total_mined": 104569,
      "total_raided": 0,
      "power_delta_7d": 225305
    },
    {
      "alliance_id": 3609329286,
      "alliance_tag": "HQ",
      "rank": 103,
      "member_count": 1,
      "total_power": 212469,
      "avg_level": 18,
      "max_level": 18,
      "total_pvp": 0,
      "total_hk": 555,
      "total_mined": 436876,
      "total_raided": 0,
      "power_delta_7d": 212469
    },
    {
      "alliance_id": 159341516,
      "alliance_tag": "RED",
      "rank": 104,
      "member_count": 3,
      "total_power": 205571,
      "avg_level": 13,
      "max_level": 15,
      "total_pvp": 7,
      "total_hk": 530,
      "total_mined": 23399,
      "total_raided": 1201,
      "power_delta_7d": 205571
    },
    {
      "alliance_id": 1378638916,
      "alliance_tag": "BEES",
      "rank": 105,
      "member_count": 1,
      "total_power": 203441,
      "avg_level": 19,
      "max_level": 19,
      "total_pvp": 0,
      "total_hk": 196,
      "total_mined": 0,
      "total_raided": 0,
      "power_delta_7d": 203441
    },
    {
      "alliance_id": 1852510639,
      "alliance_tag": "HERO",
      "rank": 106,
      "member_count": 1,
      "total_power": 191810,
      "avg_level": 16,
      "max_level": 16,
      "total_pvp": 3,
      "total_hk": 2612,
      "total_mined": 775008,
      "total_raided": 681,
      "power_delta_7d": 191810
    },
    {
      "alliance_id": 1484849975,
      "alliance_tag": "YUU",
      "rank": 107,
      "member_count": 2,
      "total_power": 190170,
      "avg_level": 17,
      "max_level": 17,
      "total_pvp": 0,
      "total_hk": 269,
      "total_mined": 7312,
      "total_raided": 0,
      "power_delta_7d": 190170
    },
    {
      "alliance_id": 4123991968,
      "alliance_tag": "BILL",
      "rank": 108,
      "member_count": 1,
      "total_power": 188479,
      "avg_level": 17,
      "max_level": 17,
      "total_pvp": 1,
      "total_hk": 431,
      "total_mined": 61383,
      "total_raided": 0,
      "power_delta_7d": 188479
    },
    {
      "alliance_id": 1085304108,
      "alliance_tag": "TREK",
      "rank": 109,
      "member_count": 1,
      "total_power": 185032,
      "avg_level": 18,
      "max_level": 18,
      "total_pvp": 46,
      "total_hk": 849,
      "total_mined": 285217,
      "total_raided": 871,
      "power_delta_7d": 185032
    },
    {
      "alliance_id": 242248362,
      "alliance_tag": "GRDN",
      "rank": 110,
      "member_count": 1,
      "total_power": 177230,
      "avg_level": 18,
      "max_level": 18,
      "total_pvp": 0,
      "total_hk": 72,
      "total_mined": 13297,
      "total_raided": 0,
      "power_delta_7d": 177230
    },
    {
      "alliance_id": 3469315603,
      "alliance_tag": "LVUP",
      "rank": 111,
      "member_count": 1,
      "total_power": 173528,
      "avg_level": 14,
      "max_level": 14,
      "total_pvp": 29,
      "total_hk": 1716,
      "total_mined": 1022940,
      "total_raided": 7234,
      "power_delta_7d": 173528
    },
    {
      "alliance_id": 4139285093,
      "alliance_tag": "GOME",
      "rank": 112,
      "member_count": 1,
      "total_power": 170804,
      "avg_level": 17,
      "max_level": 17,
      "total_pvp": 150,
      "total_hk": 1404,
      "total_mined": 132764,
      "total_raided": 17102,
      "power_delta_7d": 170804
    },
    {
      "alliance_id": 294536504,
      "alliance_tag": "DYBS",
      "rank": 113,
      "member_count": 2,
      "total_power": 170687,
      "avg_level": 14,
      "max_level": 16,
      "total_pvp": 14,
      "total_hk": 414,
      "total_mined": 56006,
      "total_raided": 3373,
      "power_delta_7d": 170687
    },
    {
      "alliance_id": 3597923509,
      "alliance_tag": "SMBA",
      "rank": 114,
      "member_count": 1,
      "total_power": 168055,
      "avg_level": 17,
      "max_level": 17,
      "total_pvp": 3,
      "total_hk": 1487,
      "total_mined": 327379,
      "total_raided": 1768,
      "power_delta_7d": 168055
    },
    {
      "alliance_id": 716729545,
      "alliance_tag": "FROG",
      "rank": 115,
      "member_count": 1,
      "total_power": 167786,
      "avg_level": 17,
      "max_level": 17,
      "total_pvp": 4,
      "total_hk": 516,
      "total_mined": 86614,
      "total_raided": 0,
      "power_delta_7d": 167786
    },
    {
      "alliance_id": 622489030,
      "alliance_tag": "KILO",
      "rank": 116,
      "member_count": 1,
      "total_power": 164221,
      "avg_level": 14,
      "max_level": 14,
      "total_pvp": 72,
      "total_hk": 750,
      "total_mined": 340728,
      "total_raided": 8898,
      "power_delta_7d": 164221
    },
    {
      "alliance_id": 3837605005,
      "alliance_tag": "LOVE",
      "rank": 117,
      "member_count": 1,
      "total_power": 164113,
      "avg_level": 17,
      "max_level": 17,
      "total_pvp": 2,
      "total_hk": 638,
      "total_mined": 311633,
      "total_raided": 414,
      "power_delta_7d": 164113
    },
    {
      "alliance_id": 315464585,
      "alliance_tag": "TRED",
      "rank": 118,
      "member_count": 1,
      "total_power": 161502,
      "avg_level": 17,
      "max_level": 17,
      "total_pvp": 0,
      "total_hk": 630,
      "total_mined": 70917,
      "total_raided": 0,
      "power_delta_7d": 161502
    },
    {
      "alliance_id": 1356337355,
      "alliance_tag": "KJS",
      "rank": 119,
      "member_count": 1,
      "total_power": 159145,
      "avg_level": 15,
      "max_level": 15,
      "total_pvp": 4,
      "total_hk": 310,
      "total_mined": 79764,
      "total_raided": 131,
      "power_delta_7d": 159145
    },
    {
      "alliance_id": 1159506030,
      "alliance_tag": "LONR",
      "rank": 120,
      "member_count": 1,
      "total_power": 156565,
      "avg_level": 14,
      "max_level": 14,
      "total_pvp": 3,
      "total_hk": 1075,
      "total_mined": 91448,
      "total_raided": 672,
      "power_delta_7d": 156565
    },
    {
      "alliance_id": 3671302607,
      "alliance_tag": "RAC",
      "rank": 121,
      "member_count": 1,
      "total_power": 155646,
      "avg_level": 15,
      "max_level": 15,
      "total_pvp": 0,
      "total_hk": 355,
      "total_mined": 30829,
      "total_raided": 0,
      "power_delta_7d": 155646
    },
    {
      "alliance_id": 3694684467,
      "alliance_tag": "FOX",
      "rank": 122,
      "member_count": 1,
      "total_power": 151897,
      "avg_level": 16,
      "max_level": 16,
      "total_pvp": 3,
      "total_hk": 315,
      "total_mined": 54731,
      "total_raided": 0,
      "power_delta_7d": 151897
    },
    {
      "alliance_id": 3611783003,
      "alliance_tag": "BLUE",
      "rank": 123,
      "member_count": 1,
      "total_power": 151886,
      "avg_level": 15,
      "max_level": 15,
      "total_pvp": 61,
      "total_hk": 396,
      "total_mined": 136671,
      "total_raided": 23948,
      "power_delta_7d": 151886
    },
    {
      "alliance_id": 944286889,
      "alliance_tag": "OPS",
      "rank": 124,
      "member_count": 1,
      "total_power": 149551,
      "avg_level": 14,
      "max_level": 14,
      "total_pvp": 0,
      "total_hk": 741,
      "total_mined": 97715,
      "total_raided": 0,
      "power_delta_7d": 149551
    },
    {
      "alliance_id": 2785383534,
      "alliance_tag": "OPEN",
      "rank": 125,
      "member_count": 1,
      "total_power": 137991,
      "avg_level": 15,
      "max_level": 15,
      "total_pvp": 9,
      "total_hk": 313,
      "total_mined": 44153,
      "total_raided": 909,
      "power_delta_7d": 137991
    },
    {
      "alliance_id": 2021316072,
      "alliance_tag": "BLAH",
      "rank": 126,
      "member_count": 2,
      "total_power": 137977,
      "avg_level": 14,
      "max_level": 16,
      "total_pvp": 0,
      "total_hk": 870,
      "total_mined": 30367,
      "total_raided": 0,
      "power_delta_7d": 137977
    },
    {
      "alliance_id": 315397731,
      "alliance_tag": "LUV",
      "rank": 127,
      "member_count": 1,
      "total_power": 135999,
      "avg_level": 15,
      "max_level": 15,
      "total_pvp": 0,
      "total_hk": 353,
      "total_mined": 134099,
      "total_raided": 0,
      "power_delta_7d": 135999
    },
    {
      "alliance_id": 3777902857,
      "alliance_tag": "AGT",
      "rank": 128,
      "member_count": 1,
      "total_power": 135716,
      "avg_level": 16,
      "max_level": 16,
      "total_pvp": 5,
      "total_hk": 657,
      "total_mined": 55767,
      "total_raided": 629,
      "power_delta_7d": 135716
    },
    {
      "alliance_id": 1672529324,
      "alliance_tag": "NCS",
      "rank": 129,
      "member_count": 1,
      "total_power": 131861,
      "avg_level": 16,
      "max_level": 16,
      "total_pvp": 1,
      "total_hk": 252,
      "total_mined": 18057,
      "total_raided": 0,
      "power_delta_7d": 131861
    },
    {
      "alliance_id": 2026074051,
      "alliance_tag": "SPC",
      "rank": 130,
      "member_count": 1,
      "total_power": 131782,
      "avg_level": 14,
      "max_level": 14,
      "total_pvp": 3,
      "total_hk": 623,
      "total_mined": 61862,
      "total_raided": 0,
      "power_delta_7d": 131782
    },
    {
      "alliance_id": 2773370283,
      "alliance_tag": "WAR",
      "rank": 131,
      "member_count": 1,
      "total_power": 125727,
      "avg_level": 16,
      "max_level": 16,
      "total_pvp": 1,
      "total_hk": 324,
      "total_mined": 49736,
      "total_raided": 0,
      "power_delta_7d": 125727
    },
    {
      "alliance_id": 3034317347,
      "alliance_tag": "PHA",
      "rank": 132,
      "member_count": 1,
      "total_power": 121999,
      "avg_level": 14,
      "max_level": 14,
      "total_pvp": 0,
      "total_hk": 639,
      "total_mined": 476594,
      "total_raided": 0,
      "power_delta_7d": 121999
    },
    {
      "alliance_id": 2214979404,
      "alliance_tag": "JF",
      "rank": 133,
      "member_count": 1,
      "total_power": 121252,
      "avg_level": 15,
      "max_level": 15,
      "total_pvp": 2,
      "total_hk": 513,
      "total_mined": 38096,
      "total_raided": 511,
      "power_delta_7d": 121252
    },
    {
      "alliance_id": 982870602,
      "alliance_tag": "CUC",
      "rank": 134,
      "member_count": 1,
      "total_power": 117654,
      "avg_level": 15,
      "max_level": 15,
      "total_pvp": 1,
      "total_hk": 86,
      "total_mined": 0,
      "total_raided": 300,
      "power_delta_7d": 117654
    },
    {
      "alliance_id": 49669309,
      "alliance_tag": "GIO",
      "rank": 135,
      "member_count": 1,
      "total_power": 117238,
      "avg_level": 15,
      "max_level": 15,
      "total_pvp": 1,
      "total_hk": 513,
      "total_mined": 55225,
      "total_raided": 0,
      "power_delta_7d": 117238
    },
    {
      "alliance_id": 1532538513,
      "alliance_tag": "ZAZA",
      "rank": 136,
      "member_count": 1,
      "total_power": 117064,
      "avg_level": 17,
      "max_level": 17,
      "total_pvp": 0,
      "total_hk": 93,
      "total_mined": 3434,
      "total_raided": 0,
      "power_delta_7d": 117064
    },
    {
      "alliance_id": 2643374868,
      "alliance_tag": "WOLF",
      "rank": 137,
      "member_count": 1,
      "total_power": 115780,
      "avg_level": 15,
      "max_level": 15,
      "total_pvp": 1,
      "total_hk": 167,
      "total_mined": 8556,
      "total_raided": 0,
      "power_delta_7d": 115780
    },
    {
      "alliance_id": 3673291994,
      "alliance_tag": "TRUL",
      "rank": 138,
      "member_count": 1,
      "total_power": 110799,
      "avg_level": 13,
      "max_level": 13,
      "total_pvp": 414,
      "total_hk": 632,
      "total_mined": 281716,
      "total_raided": 72071,
      "power_delta_7d": 110799
    },
    {
      "alliance_id": 1747483912,
      "alliance_tag": "TTV",
      "rank": 139,
      "member_count": 1,
      "total_power": 104879,
      "avg_level": 17,
      "max_level": 17,
      "total_pvp": 1,
      "total_hk": 57,
      "total_mined": 0,
      "total_raided": 0,
      "power_delta_7d": 104879
    },
    {
      "alliance_id": 4058501811,
      "alliance_tag": "SUP",
      "rank": 140,
      "member_count": 1,
      "total_power": 100264,
      "avg_level": 14,
      "max_level": 14,
      "total_pvp": 0,
      "total_hk": 2423,
      "total_mined": 43161,
      "total_raided": 0,
      "power_delta_7d": 100264
    },
    {
      "alliance_id": 1904193425,
      "alliance_tag": "BUCK",
      "rank": 141,
      "member_count": 1,
      "total_power": 98424,
      "avg_level": 15,
      "max_level": 15,
      "total_pvp": 0,
      "total_hk": 555,
      "total_mined": 170028,
      "total_raided": 0,
      "power_delta_7d": 98424
    },
    {
      "alliance_id": 862508020,
      "alliance_tag": "BAB",
      "rank": 142,
      "member_count": 1,
      "total_power": 96483,
      "avg_level": 16,
      "max_level": 16,
      "total_pvp": 0,
      "total_hk": 95,
      "total_mined": 1934,
      "total_raided": 0,
      "power_delta_7d": 96483
    },
    {
      "alliance_id": 3764324502,
      "alliance_tag": "UNI",
      "rank": 143,
      "member_count": 1,
      "total_power": 95755,
      "avg_level": 15,
      "max_level": 15,
      "total_pvp": 0,
      "total_hk": 142,
      "total_mined": 857,
      "total_raided": 0,
      "power_delta_7d": 95755
    },
    {
      "alliance_id": 2974146789,
      "alliance_tag": "SCQC",
      "rank": 144,
      "member_count": 1,
      "total_power": 89940,
      "avg_level": 14,
      "max_level": 14,
      "total_pvp": 0,
      "total_hk": 9,
      "total_mined": 0,
      "total_raided": 0,
      "power_delta_7d": 89940
    },
    {
      "alliance_id": 2752858143,
      "alliance_tag": "TEAM",
      "rank": 145,
      "member_count": 1,
      "total_power": 89504,
      "avg_level": 14,
      "max_level": 14,
      "total_pvp": 3,
      "total_hk": 659,
      "total_mined": 7945,
      "total_raided": 340,
      "power_delta_7d": 89504
    },
    {
      "alliance_id": 4138695700,
      "alliance_tag": "MMX",
      "rank": 146,
      "member_count": 1,
      "total_power": 89048,
      "avg_level": 12,
      "max_level": 12,
      "total_pvp": 7,
      "total_hk": 272,
      "total_mined": 29575,
      "total_raided": 229,
      "power_delta_7d": 89048
    },
    {
      "alliance_id": 495107868,
      "alliance_tag": "EMFD",
      "rank": 147,
      "member_count": 1,
      "total_power": 88510,
      "avg_level": 15,
      "max_level": 15,
      "total_pvp": 0,
      "total_hk": 106,
      "total_mined": 454,
      "total_raided": 0,
      "power_delta_7d": 88510
    },
    {
      "alliance_id": 1938213308,
      "alliance_tag": "SBA",
      "rank": 148,
      "member_count": 1,
      "total_power": 83094,
      "avg_level": 12,
      "max_level": 12,
      "total_pvp": 4,
      "total_hk": 173,
      "total_mined": 15659,
      "total_raided": 3486,
      "power_delta_7d": 83094
    },
    {
      "alliance_id": 2733162137,
      "alliance_tag": "FOL",
      "rank": 149,
      "member_count": 1,
      "total_power": 80080,
      "avg_level": 14,
      "max_level": 14,
      "total_pvp": 3,
      "total_hk": 349,
      "total_mined": 0,
      "total_raided": 0,
      "power_delta_7d": 80080
    },
    {
      "alliance_id": 50305719,
      "alliance_tag": "YYUU",
      "rank": 150,
      "member_count": 1,
      "total_power": 76579,
      "avg_level": 15,
      "max_level": 15,
      "total_pvp": 0,
      "total_hk": 85,
      "total_mined": 303,
      "total_raided": 0,
      "power_delta_7d": 76579
    },
    {
      "alliance_id": 2435416661,
      "alliance_tag": "KEXY",
      "rank": 151,
      "member_count": 1,
      "total_power": 75186,
      "avg_level": 15,
      "max_level": 15,
      "total_pvp": 4,
      "total_hk": 213,
      "total_mined": 2268,
      "total_raided": 135,
      "power_delta_7d": 75186
    },
    {
      "alliance_id": 1987502001,
      "alliance_tag": "DLSS",
      "rank": 152,
      "member_count": 1,
      "total_power": 73237,
      "avg_level": 14,
      "max_level": 14,
      "total_pvp": 2,
      "total_hk": 104,
      "total_mined": 23509,
      "total_raided": 1500,
      "power_delta_7d": 73237
    },
    {
      "alliance_id": 166679041,
      "alliance_tag": "GGS",
      "rank": 153,
      "member_count": 1,
      "total_power": 66836,
      "avg_level": 15,
      "max_level": 15,
      "total_pvp": 0,
      "total_hk": 105,
      "total_mined": 3,
      "total_raided": 0,
      "power_delta_7d": 66836
    },
    {
      "alliance_id": 1797346833,
      "alliance_tag": "HAT",
      "rank": 154,
      "member_count": 1,
      "total_power": 66580,
      "avg_level": 15,
      "max_level": 15,
      "total_pvp": 0,
      "total_hk": 32,
      "total_mined": 0,
      "total_raided": 0,
      "power_delta_7d": 66580
    },
    {
      "alliance_id": 3719839066,
      "alliance_tag": "LSD",
      "rank": 155,
      "member_count": 1,
      "total_power": 66562,
      "avg_level": 14,
      "max_level": 14,
      "total_pvp": 4,
      "total_hk": 214,
      "total_mined": 17349,
      "total_raided": 3690,
      "power_delta_7d": 66562
    },
    {
      "alliance_id": 4199991412,
      "alliance_tag": "PEB",
      "rank": 156,
      "member_count": 1,
      "total_power": 65652,
      "avg_level": 12,
      "max_level": 12,
      "total_pvp": 74,
      "total_hk": 261,
      "total_mined": 134793,
      "total_raided": 13052,
      "power_delta_7d": 65652
    },
    {
      "alliance_id": 819257521,
      "alliance_tag": "TG",
      "rank": 157,
      "member_count": 1,
      "total_power": 63559,
      "avg_level": 13,
      "max_level": 13,
      "total_pvp": 2,
      "total_hk": 200,
      "total_mined": 15689,
      "total_raided": 0,
      "power_delta_7d": 63559
    },
    {
      "alliance_id": 511511453,
      "alliance_tag": "THIC",
      "rank": 158,
      "member_count": 1,
      "total_power": 60996,
      "avg_level": 15,
      "max_level": 15,
      "total_pvp": 0,
      "total_hk": 20,
      "total_mined": 0,
      "total_raided": 0,
      "power_delta_7d": 60996
    },
    {
      "alliance_id": 3127893920,
      "alliance_tag": "DWM",
      "rank": 159,
      "member_count": 1,
      "total_power": 59491,
      "avg_level": 13,
      "max_level": 13,
      "total_pvp": 1,
      "total_hk": 1028,
      "total_mined": 66654,
      "total_raided": 0,
      "power_delta_7d": 59491
    },
    {
      "alliance_id": 1345227635,
      "alliance_tag": "SWC",
      "rank": 160,
      "member_count": 1,
      "total_power": 55456,
      "avg_level": 13,
      "max_level": 13,
      "total_pvp": 0,
      "total_hk": 178,
      "total_mined": 12922,
      "total_raided": 0,
      "power_delta_7d": 55456
    },
    {
      "alliance_id": 1803055613,
      "alliance_tag": "SNAK",
      "rank": 161,
      "member_count": 1,
      "total_power": 55090,
      "avg_level": 14,
      "max_level": 14,
      "total_pvp": 2,
      "total_hk": 212,
      "total_mined": 15311,
      "total_raided": 0,
      "power_delta_7d": 55090
    },
    {
      "alliance_id": 1487985973,
      "alliance_tag": "VTUB",
      "rank": 162,
      "member_count": 2,
      "total_power": 49503,
      "avg_level": 12,
      "max_level": 13,
      "total_pvp": 0,
      "total_hk": 91,
      "total_mined": 5000,
      "total_raided": 0,
      "power_delta_7d": 49503
    },
    {
      "alliance_id": 916584490,
      "alliance_tag": "CRAL",
      "rank": 163,
      "member_count": 1,
      "total_power": 47113,
      "avg_level": 14,
      "max_level": 14,
      "total_pvp": 1,
      "total_hk": 343,
      "total_mined": 19119,
      "total_raided": 0,
      "power_delta_7d": 47113
    },
    {
      "alliance_id": 3499717928,
      "alliance_tag": "CASH",
      "rank": 164,
      "member_count": 1,
      "total_power": 46546,
      "avg_level": 14,
      "max_level": 14,
      "total_pvp": 0,
      "total_hk": 42,
      "total_mined": 0,
      "total_raided": 0,
      "power_delta_7d": 46546
    },
    {
      "alliance_id": 400502486,
      "alliance_tag": "VENT",
      "rank": 165,
      "member_count": 1,
      "total_power": 46535,
      "avg_level": 13,
      "max_level": 13,
      "total_pvp": 0,
      "total_hk": 112,
      "total_mined": 2589,
      "total_raided": 0,
      "power_delta_7d": 46535
    },
    {
      "alliance_id": 128962505,
      "alliance_tag": "MAZ",
      "rank": 166,
      "member_count": 1,
      "total_power": 46018,
      "avg_level": 14,
      "max_level": 14,
      "total_pvp": 3,
      "total_hk": 274,
      "total_mined": 74116,
      "total_raided": 5314,
      "power_delta_7d": 46018
    },
    {
      "alliance_id": 1594929008,
      "alliance_tag": "AIG",
      "rank": 167,
      "member_count": 1,
      "total_power": 42793,
      "avg_level": 11,
      "max_level": 11,
      "total_pvp": 0,
      "total_hk": 160,
      "total_mined": 25138,
      "total_raided": 0,
      "power_delta_7d": 42793
    },
    {
      "alliance_id": 4022441934,
      "alliance_tag": "DBL",
      "rank": 168,
      "member_count": 1,
      "total_power": 40006,
      "avg_level": 12,
      "max_level": 12,
      "total_pvp": 0,
      "total_hk": 38,
      "total_mined": 0,
      "total_raided": 0,
      "power_delta_7d": 40006
    },
    {
      "alliance_id": 1141397216,
      "alliance_tag": "LOCO",
      "rank": 169,
      "member_count": 1,
      "total_power": 39973,
      "avg_level": 12,
      "max_level": 12,
      "total_pvp": 1,
      "total_hk": 184,
      "total_mined": 319,
      "total_raided": 0,
      "power_delta_7d": 39973
    },
    {
      "alliance_id": 1717114898,
      "alliance_tag": "OOPS",
      "rank": 170,
      "member_count": 1,
      "total_power": 39162,
      "avg_level": 12,
      "max_level": 12,
      "total_pvp": 0,
      "total_hk": 59,
      "total_mined": 0,
      "total_raided": 0,
      "power_delta_7d": 39162
    },
    {
      "alliance_id": 2016040320,
      "alliance_tag": "STOR",
      "rank": 171,
      "member_count": 1,
      "total_power": 38800,
      "avg_level": 13,
      "max_level": 13,
      "total_pvp": 2,
      "total_hk": 249,
      "total_mined": 3957,
      "total_raided": 0,
      "power_delta_7d": 38800
    },
    {
      "alliance_id": 1032889774,
      "alliance_tag": "RAWR",
      "rank": 172,
      "member_count": 1,
      "total_power": 38297,
      "avg_level": 12,
      "max_level": 12,
      "total_pvp": 0,
      "total_hk": 70,
      "total_mined": 0,
      "total_raided": 0,
      "power_delta_7d": 38297
    },
    {
      "alliance_id": 3028707262,
      "alliance_tag": "BC",
      "rank": 173,
      "member_count": 1,
      "total_power": 32906,
      "avg_level": 12,
      "max_level": 12,
      "total_pvp": 0,
      "total_hk": 496,
      "total_mined": 10406,
      "total_raided": 0,
      "power_delta_7d": 32906
    },
    {
      "alliance_id": 2514480450,
      "alliance_tag": "QS",
      "rank": 174,
      "member_count": 1,
      "total_power": 27302,
      "avg_level": 11,
      "max_level": 11,
      "total_pvp": 0,
      "total_hk": 44,
      "total_mined": 3939,
      "total_raided": 0,
      "power_delta_7d": 27302
    },
    {
      "alliance_id": 550608380,
      "alliance_tag": "JAY",
      "rank": 175,
      "member_count": 1,
      "total_power": 21879,
      "avg_level": 12,
      "max_level": 12,
      "total_pvp": 0,
      "total_hk": 25,
      "total_mined": 0,
      "total_raided": 0,
      "power_delta_7d": 21879
    }
  ]
}